.gitignore
LICENSE.md
MANIFEST.in
README.md
setup.py
FSMakeROI.egg-info/PKG-INFO
FSMakeROI.egg-info/SOURCES.txt
FSMakeROI.egg-info/dependency_links.txt
FSMakeROI.egg-info/entry_points.txt
FSMakeROI.egg-info/requires.txt
FSMakeROI.egg-info/top_level.txt
examples/example_roi.txt
fsmakeroi/FsTutorial_AnatomicalROI_FreeSurferColorLUT.txt
fsmakeroi/__init__.py
fsmakeroi/fsmakeroi.py
fsmakeroi/info.py
fsmakeroi/iocontrol.py