Metadata-Version: 2.1
Name: FSMakeROI
Version: 1.2
Summary: A CLI tool to extract ROIs from Freesurfer segmentation file
Home-page: https://github.com/TheJaeger/FSMakeROI
Author: Siddhartha Dhiman
Author-email: dhiman@musc.edu
Maintainer: Siddhartha Dhiman
License: MPL 2.0
Platform: UNKNOWN
Classifier: Programming Language :: Python :: 3.7
Classifier: License :: OSI Approved :: Mozilla Public License 2.0 (MPL 2.0)
Classifier: Operating System :: OS Independent
Requires-Python: >=3.7
